LICENSE
MANIFEST.in
README.md
pyproject.toml
setup.cfg
setup.py
src/.DS_Store
src/TransDecoder-TransDecoder-v5.7.1/.DS_Store
src/TransDecoder-TransDecoder-v5.7.1/.gitmodules
src/TransDecoder-TransDecoder-v5.7.1/Changelog.txt
src/TransDecoder-TransDecoder-v5.7.1/LICENSE.txt
src/TransDecoder-TransDecoder-v5.7.1/Makefile
src/TransDecoder-TransDecoder-v5.7.1/README.md
src/TransDecoder-TransDecoder-v5.7.1/TransDecoder.LongOrfs
src/TransDecoder-TransDecoder-v5.7.1/TransDecoder.Predict
src/TransDecoder-TransDecoder-v5.7.1/notes
src/TransDecoder-TransDecoder-v5.7.1/Docker/Dockerfile
src/TransDecoder-TransDecoder-v5.7.1/Docker/VERSION.txt
src/TransDecoder-TransDecoder-v5.7.1/Docker/build_docker.sh
src/TransDecoder-TransDecoder-v5.7.1/Docker/make_simg.sh
src/TransDecoder-TransDecoder-v5.7.1/Docker/push_docker.sh
src/TransDecoder-TransDecoder-v5.7.1/PerlLib/DelimParser.pm
src/TransDecoder-TransDecoder-v5.7.1/PerlLib/Fasta_reader.pm
src/TransDecoder-TransDecoder-v5.7.1/PerlLib/Fasta_retriever.pm
src/TransDecoder-TransDecoder-v5.7.1/PerlLib/GFF3_utils2.pm
src/TransDecoder-TransDecoder-v5.7.1/PerlLib/GTF.pm
src/TransDecoder-TransDecoder-v5.7.1/PerlLib/GTF_utils2.pm
src/TransDecoder-TransDecoder-v5.7.1/PerlLib/Gene_obj.pm
src/TransDecoder-TransDecoder-v5.7.1/PerlLib/Longest_orf.pm
src/TransDecoder-TransDecoder-v5.7.1/PerlLib/Nuc_translator.pm
src/TransDecoder-TransDecoder-v5.7.1/PerlLib/Overlap_piler.pm
src/TransDecoder-TransDecoder-v5.7.1/PerlLib/PWM.pm
src/TransDecoder-TransDecoder-v5.7.1/PerlLib/Pipeliner.pm
src/TransDecoder-TransDecoder-v5.7.1/PerlLib/Process_cmd.pm
src/TransDecoder-TransDecoder-v5.7.1/PerlLib/overlapping_nucs.ph
src/TransDecoder-TransDecoder-v5.7.1/__testing/Makefile
src/TransDecoder-TransDecoder-v5.7.1/__testing/__test.best_w_homology.expected
src/TransDecoder-TransDecoder-v5.7.1/__testing/__test.simplest.expected
src/TransDecoder-TransDecoder-v5.7.1/__testing/__test.single_best.expected
src/isoespy.egg-info/PKG-INFO
src/isoespy.egg-info/SOURCES.txt
src/isoespy.egg-info/dependency_links.txt
src/isoespy.egg-info/entry_points.txt
src/isoespy.egg-info/requires.txt
src/isoespy.egg-info/top_level.txt