Metadata-Version: 2.1
Name: isoespy
Version: 0.0.1
Summary: This package visualizes isoform structures, expression levels and functiona features.
Home-page: https://github.com/kolikem/isoespy
Author: Ko Ikemoto
Author-email: imko@m.u-tokyo.ac.jp
Requires-Python: >=3.7
License-File: LICENSE
Requires-Dist: matplotlib>=3.5
Requires-Dist: pandas>=1.3
Requires-Dist: numpy>=1.21
Requires-Dist: seaborn>=0.10.0
Requires-Dist: pysam>=0.20.0
